{"nodes":

[{"name":"Proyecto 1","group":1},
{"name":"Proyecto 2","group":1},
{"name":"Proyecto 3","group":1},
{"name":"Proyecto 4","group":1},
{"name":"Proyecto 5","group":1},
{"name":"Proyecto 6","group":1},
{"name":"Proyecto 7","group":1},
{"name":"Persona 1","group":2},
{"name":"Persona 2","group":2},
{"name":"Persona 3","group":2},
{"name":"Persona 4","group":2},
{"name":"Persona 5","group":2},
{"name":"Persona 6","group":2},
{"name":"Persona 7","group":2}],

"links":[{"source":0,"target":11,"value":1},
{"source":0,"target":7,"value":1},
{"source":0,"target":8,"value":1},
{"source":1,"target":9,"value":1},
{"source":2,"target":10,"value":1},
{"source":3,"target":11,"value":1},
{"source":4,"target":11,"value":1},
{"source":6,"target":12,"value":1},
{"source":6,"target":13,"value":1},
{"source":5,"target":11,"value":1}
]}